odoo/addons/stock_move_source_relocate/README.rst
odoo/addons/stock_move_source_relocate/__init__.py
odoo/addons/stock_move_source_relocate/__manifest__.py
odoo/addons/stock_move_source_relocate/i18n/es_AR.po
odoo/addons/stock_move_source_relocate/i18n/stock_move_source_relocate.pot
odoo/addons/stock_move_source_relocate/models/__init__.py
odoo/addons/stock_move_source_relocate/models/stock_move.py
odoo/addons/stock_move_source_relocate/models/stock_source_relocate.py
odoo/addons/stock_move_source_relocate/readme/CONFIGURE.rst
odoo/addons/stock_move_source_relocate/readme/CONTRIBUTORS.rst
odoo/addons/stock_move_source_relocate/readme/DESCRIPTION.rst
odoo/addons/stock_move_source_relocate/security/ir.model.access.csv
odoo/addons/stock_move_source_relocate/static/description/icon.png
odoo/addons/stock_move_source_relocate/static/description/index.html
odoo/addons/stock_move_source_relocate/tests/__init__.py
odoo/addons/stock_move_source_relocate/tests/test_source_relocate.py
odoo/addons/stock_move_source_relocate/views/stock_source_relocate_views.xml
odoo13_addon_stock_move_source_relocate-13.0.1.1.0.dist-info/METADATA
odoo13_addon_stock_move_source_relocate-13.0.1.1.0.dist-info/WHEEL
odoo13_addon_stock_move_source_relocate-13.0.1.1.0.dist-info/top_level.txt
odoo13_addon_stock_move_source_relocate-13.0.1.1.0.dist-info/RECORD
